{"lastUsed":1617257909087,"path":"E:\/Exercise\/Spring\/luv2Code","projectCount":1,"recentFiles":[{"path":"\/hb-03-one-to-many\/src\/com\/luv2code\/hibernate\/demo\/entity","parentWorkspace":"E:\/Exercise\/Spring\/luv2Code","name":"Instructor.java","lastModified":1617257758302,"locationURI":"file:\/E:\/Exercise\/Spring\/luv2Code\/hb-03-one-to-many\/src\/com\/luv2code\/hibernate\/demo\/entity\/Instructor.java"},{"path":"\/hb-03-one-to-many\/src\/com\/luv2code\/hibernate\/demo\/entity","parentWorkspace":"E:\/Exercise\/Spring\/luv2Code","name":"Course.java","lastModified":1617254422021,"locationURI":"file:\/E:\/Exercise\/Spring\/luv2Code\/hb-03-one-to-many\/src\/com\/luv2code\/hibernate\/demo\/entity\/Course.java"}]}